aiida_kkr/__init__.py
aiida_kkr/calculations/__init__.py
aiida_kkr/calculations/kkr.py
aiida_kkr/calculations/kkrimp.py
aiida_kkr/calculations/kkrimporter.py
aiida_kkr/calculations/kkrnano.py
aiida_kkr/calculations/voro.py
aiida_kkr/cmdline/__init__.py
aiida_kkr/cmdline/data/__init__.py
aiida_kkr/cmdline/data/parameters.py
aiida_kkr/cmdline/data/structure.py
aiida_kkr/cmdline/launch/__init__.py
aiida_kkr/cmdline/launch/launch.py
aiida_kkr/cmdline/util/__init__.py
aiida_kkr/cmdline/util/defaults.py
aiida_kkr/cmdline/util/options.py
aiida_kkr/cmdline/util/types.py
aiida_kkr/cmdline/util/utils.py
aiida_kkr/cmdline/visualization/__init__.py
aiida_kkr/data/__init__.py
aiida_kkr/data/kkrstructure.py
aiida_kkr/data/strucwithpot.py
aiida_kkr/parsers/__init__.py
aiida_kkr/parsers/kkr.py
aiida_kkr/parsers/kkrimp.py
aiida_kkr/parsers/kkrimporter.py
aiida_kkr/parsers/kkrnano.py
aiida_kkr/parsers/voro.py
aiida_kkr/tools/__init__.py
aiida_kkr/tools/bdg_tools.py
aiida_kkr/tools/combine_imps.py
aiida_kkr/tools/common_workfunctions.py
aiida_kkr/tools/context.py
aiida_kkr/tools/dict_util.py
aiida_kkr/tools/extract_kkrhost_noco_angles.py
aiida_kkr/tools/find_cluster_radius.py
aiida_kkr/tools/find_parent.py
aiida_kkr/tools/imp_cluster_tools.py
aiida_kkr/tools/jij_tools.py
aiida_kkr/tools/kick_out_core_states.py
aiida_kkr/tools/ldau.py
aiida_kkr/tools/make_supercell.py
aiida_kkr/tools/multi_imps_data_extract.py
aiida_kkr/tools/neworder_potential.py
aiida_kkr/tools/parse_dos.py
aiida_kkr/tools/plot_kkr.py
aiida_kkr/tools/save_output_nodes.py
aiida_kkr/tools/tools_STM_scan.py
aiida_kkr/tools/tools_kkrimp.py
aiida_kkr/workflows/KKRnanoDOSChain.py
aiida_kkr/workflows/__init__.py
aiida_kkr/workflows/_combine_imps.py
aiida_kkr/workflows/_decimation.py
aiida_kkr/workflows/base_restart_calc.py
aiida_kkr/workflows/bs.py
aiida_kkr/workflows/dos.py
aiida_kkr/workflows/eos.py
aiida_kkr/workflows/gf_writeout.py
aiida_kkr/workflows/imp_BdG.py
aiida_kkr/workflows/jijs.py
aiida_kkr-2.3.1.dist-info/entry_points.txt
aiida_kkr-2.3.1.dist-info/LICENSE.txt
aiida_kkr-2.3.1.dist-info/WHEEL
aiida_kkr-2.3.1.dist-info/METADATA
aiida_kkr-2.3.1.dist-info/RECORD
