Metadata-Version: 2.3
Name: aiida-kkr
Version: 2.3.1
Summary: AiiDA plugin for the JuKKR codes
Keywords: material science,aiida,dft,all-electron,kkr
Author-email: Philipp Ruessmann <p.ruessmann@fz-juelich.de>, Jens Broeder <j.broeder@fz-juelich.de>, Fabian Bertoldo <f.bertoldo@fz-juelich.de>
Classifier: License :: OSI Approved :: MIT License
Classifier: Programming Language :: Python :: 3
Classifier: Programming Language :: Python :: 3.7
Classifier: Programming Language :: Python :: 3.8
Classifier: Programming Language :: Python :: 3.9
Classifier: Programming Language :: Python :: 3.10
Classifier: Development Status :: 4 - Beta
Classifier: Environment :: Plugins
Classifier: Intended Audience :: Science/Research
Classifier: Topic :: Scientific/Engineering :: Physics
Classifier: Natural Language :: English
Classifier: Framework :: AiiDA
Requires-Dist: aiida-core >= 2.0.0,<3.0.0
Requires-Dist: masci-tools >= 0.4.8.dev5,<1.0.0
Requires-Dist: seekpath >= 1.9.2
Requires-Dist: ase
Requires-Dist: pymatgen
Requires-Dist: bump2version >= 0.5.10 ; extra == "devtools"
Requires-Dist: Sphinx >= 1.8.2 ; extra == "docs"
Requires-Dist: sphinx_rtd_theme >= 0.4.2 ; extra == "docs"
Requires-Dist: pre-commit >= 4.0.1 ; extra == "pre-commit"
Requires-Dist: yapf >= 0.43.0 ; extra == "pre-commit"
Requires-Dist: pylint == 1.9.4 ; extra == "pre-commit" and ( python_version < '3.0')
Requires-Dist: pylint >= 3.3.1 ; extra == "pre-commit" and ( python_version >= '3.0')
Requires-Dist: pgtest >= 1.3.0 ; extra == "testing"
Requires-Dist: pytest-xdist ; extra == "testing"
Requires-Dist: pytest-cov >= 2.5.0 ; extra == "testing"
Requires-Dist: pytest-mpl >= 0.10 ; extra == "testing"
Requires-Dist: pytest-timeout >= 1.3.3 ; extra == "testing"
Requires-Dist: pytest-regressions >= 1.0 ; extra == "testing"
Requires-Dist: MarkupSafe < 3.1.0 ; extra == "testing"
Requires-Dist: aiida-test-cache ; extra == "testing"
Requires-Dist: ase_notebook ; extra == "widgets"
Project-URL: Documentation, https://aiida-kkr.readthedocs.io
Project-URL: Download, https://github.com/JuDFTteam/aiida-kkr
Project-URL: Homepage, https://github.com/JuDFTteam/aiida-kkr
Provides-Extra: devtools
Provides-Extra: docs
Provides-Extra: pre-commit
Provides-Extra: testing
Provides-Extra: widgets
